<instance version="4" description="" template="ebps">
	<list name="extensions" comment="DO NOT USE further - but do not delete as it's reference in campaign maps&#xD;&#xA;goldenlarch is now the larch -  usin larch as the parent_pbg">
		<template_reference name="exts" value="ebpextensions\entity_blueprint_ext" List.ItemID="-1216464913" List.ParentItemID="-1216464913">
			<bool name="browsable_in_editor" value="False" overrideParent="True" />
		</template_reference>
		<template_reference name="exts" value="ebpextensions\resource_deposit_ext" List.ItemID="776156627" List.ParentItemID="776156627">
			<float name="initial_amount" value="1200" overrideParent="True" />
		</template_reference>
		<template_reference name="exts" value="ebpextensions\audio_ext" List.ItemID="457334264" List.ParentItemID="457334264">
			<list name="select_audible_to_relation_list" overrideParent="True">
				<enum name="relationship_type" value="neutral" List.ItemID="1799140470" />
			</list>
		</template_reference>
	</list>
	<uniqueid name="pbgid" value="1073741834" />
	<instance_reference name="parent_pbg" value="ebps\gameplay\resources\wood\trees\single\larch_med_wild_scatter" />
</instance>